SRC/alu_top.v
module alu_top (
    input  [7:0] A,        // Operand A
    input  [7:0] B,        // Operand B
    input  [3:0] opcode,   // Operation select
    output reg [7:0] result, // 8-bit result
    output Z,              // Zero flag
    output C,              // Carry flag
    output V,              // Overflow flag
    output N               // Negative flag
);

    // 9-bit wire to capture carry out from arithmetic ops
    reg [8:0] temp;

    always @(*) begin
        temp = 9'b0; // default
        case (opcode)
            4'b0000: temp = A + B;           // ADD
            4'b0001: temp = A - B;           // SUB
            4'b0010: temp = A + 1;           // INC
            4'b0011: temp = A - 1;           // DEC
            4'b0100: temp = A & B;           // AND
            4'b0101: temp = A | B;           // OR
            4'b0110: temp = A ^ B;           // XOR
            4'b0111: temp = ~A;              // NOT
            4'b1000: temp = ~(A & B);        // NAND
            4'b1001: temp = ~(A | B);        // NOR
            4'b1010: temp = ~(A ^ B);        // XNOR
            4'b1011: temp = A << 1;          // SHL
            4'b1100: temp = A >> 1;          // SHR
            4'b1101: temp = {A[7], A[7:1]};  // ASR (preserve sign bit)
            4'b1110: temp = A - B;           // CMP (flags only, result ignored)
            4'b1111: temp = A;               // PASS
            default: temp = 9'b0;
        endcase
        result = temp[7:0];
    end

    // Flag logic
    assign Z = (result == 8'b0);           // Zero: result is zero
    assign C = temp[8];                    // Carry: 9th bit from arithmetic
    assign N = result[7];                  // Negative: MSB of result
    assign V = (~A[7] & ~B[7] & result[7]) // Overflow: signed overflow
             | (A[7] & B[7] & ~result[7]);

endmodule

TB/alu_tb.v
`timescale 1ns/1ps  // time unit / precision

module alu_tb;

    // Declare inputs as reg (we drive these)
    reg [7:0] A;
    reg [7:0] B;
    reg [3:0] opcode;

    // Declare outputs as wire (we just listen to these)
    wire [7:0] result;
    wire Z, C, V, N;

    // Hook up the ALU (connect testbench to alu_top)
    alu_top uut (
        .A(A),
        .B(B),
        .opcode(opcode),
        .result(result),
        .Z(Z),
        .C(C),
        .V(V),
        .N(N)
    );

    // Dump waveforms to a file so GTKWave can read it
    initial begin
        $dumpfile("alu_tb.vcd");
        $dumpvars(0, alu_tb);
    end

    // Apply test cases
    initial begin
        $display("--- ALU TESTBENCH START ---");
        $display("Op\t\tA\tB\tResult\tZ C V N");
        $display("--------------------------------------------------");

        // --- ARITHMETIC ---

        // ADD: 5 + 3 = 8
        A = 8'd5; B = 8'd3; opcode = 4'b0000; #10;
        $display("ADD\t\t%0d\t%0d\t%0d\t%b %b %b %b", A, B, result, Z, C, V, N);

        // SUB: 10 - 4 = 6
        A = 8'd10; B = 8'd4; opcode = 4'b0001; #10;
        $display("SUB\t\t%0d\t%0d\t%0d\t%b %b %b %b", A, B, result, Z, C, V, N);

        // INC: 7 + 1 = 8
        A = 8'd7; B = 8'd0; opcode = 4'b0010; #10;
        $display("INC\t\t%0d\t-\t%0d\t%b %b %b %b", A, result, Z, C, V, N);

        // DEC: 7 - 1 = 6
        A = 8'd7; B = 8'd0; opcode = 4'b0011; #10;
        $display("DEC\t\t%0d\t-\t%0d\t%b %b %b %b", A, result, Z, C, V, N);

        // ADD causing Carry: 255 + 1 = overflow
        A = 8'd255; B = 8'd1; opcode = 4'b0000; #10;
        $display("ADD(carry)\t%0d\t%0d\t%0d\t%b %b %b %b", A, B, result, Z, C, V, N);

        // SUB causing Zero: 5 - 5 = 0
        A = 8'd5; B = 8'd5; opcode = 4'b0001; #10;
        $display("SUB(zero)\t%0d\t%0d\t%0d\t%b %b %b %b", A, B, result, Z, C, V, N);

        // --- LOGIC ---

        // AND: 1100 & 1010 = 1000
        A = 8'b11001100; B = 8'b10101010; opcode = 4'b0100; #10;
        $display("AND\t\t%0d\t%0d\t%0d\t%b %b %b %b", A, B, result, Z, C, V, N);

        // OR: 1100 | 1010 = 1110
        A = 8'b11001100; B = 8'b10101010; opcode = 4'b0101; #10;
        $display("OR\t\t%0d\t%0d\t%0d\t%b %b %b %b", A, B, result, Z, C, V, N);

        // XOR: 1100 ^ 1010 = 0110
        A = 8'b11001100; B = 8'b10101010; opcode = 4'b0110; #10;
        $display("XOR\t\t%0d\t%0d\t%0d\t%b %b %b %b", A, B, result, Z, C, V, N);

        // NOT: ~A
        A = 8'b11001100; B = 8'd0; opcode = 4'b0111; #10;
        $display("NOT\t\t%0d\t-\t%0d\t%b %b %b %b", A, result, Z, C, V, N);

        // --- SHIFTS ---

        // SHL: 0000 1111 << 1 = 0001 1110
        A = 8'b00001111; B = 8'd0; opcode = 4'b1011; #10;
        $display("SHL\t\t%0d\t-\t%0d\t%b %b %b %b", A, result, Z, C, V, N);

        // SHR: 0000 1111 >> 1 = 0000 0111
        A = 8'b00001111; B = 8'd0; opcode = 4'b1100; #10;
        $display("SHR\t\t%0d\t-\t%0d\t%b %b %b %b", A, result, Z, C, V, N);

        // ASR: 1000 1111 >>> 1 = 1100 0111 (sign preserved)
        A = 8'b10001111; B = 8'd0; opcode = 4'b1101; #10;
        $display("ASR\t\t%0d\t-\t%0d\t%b %b %b %b", A, result, Z, C, V, N);

        // --- UTILITY ---

        // PASS: just passes A through
        A = 8'd42; B = 8'd0; opcode = 4'b1111; #10;
        $display("PASS\t\t%0d\t-\t%0d\t%b %b %b %b", A, result, Z, C, V, N);

        $display("--------------------------------------------------");
        $display("--- ALU TESTBENCH END ---");
        $finish;
    end

endmodule

Waveforms/alu_tb.vcd
$date
	Mon May 18 20:25:01 2026
$end
$version
	Icarus Verilog
$end
$timescale
	1ps
$end
$scope module alu_tb $end
$var wire 8 ! result [7:0] $end
$var wire 1 " Z $end
$var wire 1 # V $end
$var wire 1 $ N $end
$var wire 1 % C $end
$var reg 8 & A [7:0] $end
$var reg 8 ' B [7:0] $end
$var reg 4 ( opcode [3:0] $end
$scope module uut $end
$var wire 8 ) A [7:0] $end
$var wire 8 * B [7:0] $end
$var wire 1 # V $end
$var wire 4 + opcode [3:0] $end
$var wire 1 " Z $end
$var wire 1 $ N $end
$var wire 1 % C $end
$var reg 8 , result [7:0] $end
$var reg 9 - temp [8:0] $end
$upscope $end
$upscope $end
$enddefinitions $end
$comment Show the parameter values. $end
$dumpall
$end
#0
$dumpvars
b1000 -
b1000 ,
b0 +
b11 *
b101 )
b0 (
b11 '
b101 &
0%
0$
0#
0"
b1000 !
$end
#10000
b110 !
b110 ,
b110 -
b1 (
b1 +
b100 '
b100 *
b1010 &
b1010 )
#20000
b1000 !
b1000 ,
b1000 -
b10 (
b10 +
b0 '
b0 *
b111 &
b111 )
#30000
b110 !
b110 ,
b110 -
b11 (
b11 +
#40000
1%
1"
b0 !
b0 ,
b100000000 -
b0 (
b0 +
b1 '
b1 *
b11111111 &
b11111111 )
#50000
0%
b0 -
b1 (
b1 +
b101 '
b101 *
b101 &
b101 )
#60000
0#
1$
0"
b10001000 !
b10001000 ,
b10001000 -
b100 (
b100 +
b10101010 '
b10101010 *
b11001100 &
b11001100 )
#70000
b11101110 !
b11101110 ,
b11101110 -
b101 (
b101 +
#80000
1#
0$
b1100110 !
b1100110 ,
b1100110 -
b110 (
b110 +
#90000
0#
1%
b110011 !
b110011 ,
b100110011 -
b111 (
b111 +
b0 '
b0 *
#100000
0%
b11110 !
b11110 ,
b11110 -
b1011 (
b1011 +
b1111 &
b1111 )
#110000
b111 !
b111 ,
b111 -
b1100 (
b1100 +
#120000
1$
b11000111 !
b11000111 ,
b11000111 -
b1101 (
b1101 +
b10001111 &
b10001111 )
#130000
0$
b101010 !
b101010 ,
b101010 -
b1111 (
b1111 +
b101010 &
b101010 )
